django_haystack_solr_commands-0.1.dist-info/METADATA
django_haystack_solr_commands-0.1.dist-info/top_level.txt
django_haystack_solr_commands-0.1.dist-info/RECORD
django_haystack_solr_commands-0.1.dist-info/WHEEL
django_haystack_solr_commands-0.1.dist-info/metadata.json
django_haystack_solr_commands-0.1.dist-info/DESCRIPTION.rst
haystack_solr_commands/settings.py
haystack_solr_commands/tests.py
haystack_solr_commands/__init__.py
