Metadata-Version: 2.0
Name: django-haystack-solr-commands
Version: 0.1
Summary: django management command 'solr' all-in-one for Solr 5
Home-page: https://github.com/elishowk/django-haystack-solr-commands
Author: Elias Showk
Author-email: elias@showk.me
License: MIT
Keywords: solr haystack django management
Platform: UNKNOWN
Classifier: Development Status :: 3 - Alpha
Classifier: Topic :: Utilities
Classifier: License :: OSI Approved :: BSD License
Requires-Dist: Django (>=1.4)
Requires-Dist: django-haystack (>=2.2.0)
